rhodochrosite-25.0.1.dist-info/METADATA
rhodochrosite-25.0.1.dist-info/WHEEL
rhodochrosite-25.0.1.dist-info/entry_points.txt
rhodochrosite-25.0.1.dist-info/licenses/LICENCE
rhodochrosite/__init__.py
rhodochrosite/cursor.py
rhodochrosite/exc.py
rhodochrosite/py.typed
rhodochrosite/reader.py
rhodochrosite/ruby.py
rhodochrosite/tests/remarshal/__init__.py
rhodochrosite/tests/remarshal/test_custom_marshal.py
rhodochrosite/tests/remarshal/test_marshal_objects.py
rhodochrosite/tests/remarshal/test_marshal_primitives.py
rhodochrosite/tests/remarshal/test_roundtrip.py
rhodochrosite/tests/test_finding_ivars.py
rhodochrosite/tests/test_invariants.py
rhodochrosite/tests/unmarshal/__init__.py
rhodochrosite/tests/unmarshal/test_basic_unmarshal.py
rhodochrosite/tests/unmarshal/test_custom_unmarshal.py
rhodochrosite/tests/unmarshal/test_edge_cases.py
rhodochrosite/tests/unmarshal/test_user_unmarshal.py
rhodochrosite/writer.py
rhodochrosite-25.0.1.dist-info/RECORD
