Metadata-Version: 2.4
Name: rhodochrosite
Version: 25.0.1
Summary: Ruby marshal and unmarshal library
Author-Email: Lura Skye <fuyukaii@proton.me>, Loris Lacuna <doriloris@protonmail.com>
License-Expression: GPL-3.0-or-later
Classifier: Development Status :: 5 - Production/Stable
Classifier: Programming Language :: Ruby
Project-URL: Homepage, https://codeberg.org/lacusdoloris/rhodochrosite
Requires-Python: >=3.13
Requires-Dist: attrs>=25.4.0
